dbt/adapters/__about__.py
dbt/adapters/__init__.py
dbt/adapters/cache.py
dbt/adapters/capability.py
dbt/adapters/factory.py
dbt/adapters/protocol.py
dbt/adapters/py.typed
dbt/adapters/reference_keys.py
dbt/adapters/utils.py
dbt/adapters/base/README.md
dbt/adapters/base/__init__.py
dbt/adapters/base/column.py
dbt/adapters/base/connections.py
dbt/adapters/base/impl.py
dbt/adapters/base/meta.py
dbt/adapters/base/plugin.py
dbt/adapters/base/query_headers.py
dbt/adapters/base/relation.py
dbt/adapters/catalogs/__init__.py
dbt/adapters/catalogs/_client.py
dbt/adapters/catalogs/_exceptions.py
dbt/adapters/catalogs/_integration.py
dbt/adapters/clients/__init__.py
dbt/adapters/clients/jinja.py
dbt/adapters/contracts/__init__.py
dbt/adapters/contracts/connection.py
dbt/adapters/contracts/macros.py
dbt/adapters/contracts/relation.py
dbt/adapters/events/README.md
dbt/adapters/events/__init__.py
dbt/adapters/events/adapter_types.proto
dbt/adapters/events/adapter_types_pb2.py
dbt/adapters/events/base_types.py
dbt/adapters/events/logging.py
dbt/adapters/events/types.py
dbt/adapters/exceptions/__init__.py
dbt/adapters/exceptions/alias.py
dbt/adapters/exceptions/cache.py
dbt/adapters/exceptions/compilation.py
dbt/adapters/exceptions/connection.py
dbt/adapters/exceptions/database.py
dbt/adapters/record/__init__.py
dbt/adapters/record/base.py
dbt/adapters/record/handle.py
dbt/adapters/record/serialization.py
dbt/adapters/record/cursor/cursor.py
dbt/adapters/record/cursor/description.py
dbt/adapters/record/cursor/execute.py
dbt/adapters/record/cursor/fetchall.py
dbt/adapters/record/cursor/fetchmany.py
dbt/adapters/record/cursor/fetchone.py
dbt/adapters/record/cursor/rowcount.py
dbt/adapters/relation_configs/README.md
dbt/adapters/relation_configs/__init__.py
dbt/adapters/relation_configs/config_base.py
dbt/adapters/relation_configs/config_change.py
dbt/adapters/relation_configs/config_validation.py
dbt/adapters/sql/__init__.py
dbt/adapters/sql/connections.py
dbt/adapters/sql/impl.py
in_dbt_adapters-1.14.10.dist-info/METADATA
in_dbt_adapters-1.14.10.dist-info/WHEEL
in_dbt_adapters-1.14.10.dist-info/licenses/LICENSE
in_dbt_adapters-1.14.10.dist-info/RECORD
