Metadata-Version: 2.4
Name: in-dbt-adapters
Version: 1.14.10
Summary: Release for LinkedIn's changes to dbt-adapter.The set of adapter protocols and base functionality that supports integration with dbt-core
Project-URL: Homepage, https://github.com/dbt-labs/dbt-adapters/tree/main/dbt-adapters
Project-URL: Documentation, https://docs.getdbt.com
Project-URL: Repository, https://github.com/linkedin-managed/in-dbt-adapters#subdirectory=dbt-adapters
Project-URL: Issues, https://github.com/linkedin-managed/in-dbt-adapters/issues
Project-URL: Changelog, https://github.com/linkedin-managed/in-dbt-adapters/blob/main/dbt-adapters/CHANGELOG.md
Author-email: LinkedIn DBT Team <dbt-eng@linkedin.com>
Maintainer-email: LinkedIn DBT Team <dbt-eng@linkedin.com>
License-File: LICENSE
Keywords: adapter,adapters,database,dbt,dbt Cloud,dbt Core,dbt Labs,dbt-core,elt
Classifier: Development Status :: 5 - Production/Stable
Classifier: License :: OSI Approved :: Apache Software License
Classifier: Operating System :: MacOS :: MacOS X
Classifier: Operating System :: Microsoft :: Windows
Classifier: Operating System :: POSIX :: Linux
Classifier: Programming Language :: Python :: 3.9
Classifier: Programming Language :: Python :: 3.10
Classifier: Programming Language :: Python :: 3.11
Classifier: Programming Language :: Python :: 3.12
Requires-Python: >=3.9.0
Requires-Dist: agate<2.0,>=1.0
Requires-Dist: dbt-common<2.0,>=1.13
Requires-Dist: mashumaro[msgpack]<3.15,>=3.9
Requires-Dist: protobuf<6.0,>=5.0
Requires-Dist: pytz>=2015.7
Requires-Dist: typing-extensions<5.0,>=4.0
